enhanced_print/__init__.py
enhanced_print/eprint.py
enhanced_print-0.1.0.dist-info/LICENSE
enhanced_print-0.1.0.dist-info/METADATA
enhanced_print-0.1.0.dist-info/WHEEL
enhanced_print-0.1.0.dist-info/top_level.txt
enhanced_print-0.1.0.dist-info/RECORD
