Metadata-Version: 2.1
Name: enhanced-print
Version: 0.1.0
Summary: An enhanced print function for Python with advanced features.
Home-page: https://github.com/manus-ai/enhanced_print_lib
Author: Manus AI
Author-email: manus_ai@example.com
License: UNKNOWN
Platform: UNKNOWN
Classifier: Programming Language :: Python :: 3
Classifier: License :: OSI Approved :: MIT License
Classifier: Operating System :: OS Independent
Classifier: Development Status :: 3 - Alpha
Classifier: Topic :: Software Development :: Libraries :: Python Modules
Classifier: Topic :: Utilities
Requires-Python: >=3.6
License-File: LICENSE
Requires-Dist: PyYAML
